{
  "action_id": "gov_action1q0m8z7glm9cprucwf44hdjdfra8khnakpm3hu5ueh929hvljw4aqqzuxfxz",
  "action_type": "TreasuryWithdrawals",
  "recommendation": "ABSTAIN",
  "score": 0.1167,
  "confidence": 0.6067,
  "facts": [
    "Treasury withdrawal actions require elevated scrutiny.",
    "Flag score present (7), reducing confidence."
  ],
  "inferences": [
    "Network DRep distribution used as one signal, not authority."
  ],
  "uncertainty": [
    "Rule-based system; does not infer unstated intent."
  ],
  "missing_evidence": [],
  "input_hash": "6d9cf4d030a1d6ec51847afff8258893daa5b9a1e429d874098c19d8ebc9b014",
  "snapshot_bundle_hash": "277c127bc316b5e0d22985d3178b1dba2b7ade67484dad8928b3eb9b8631e99d",
  "soul_commit": "f9f8fbe5a6ecfe866593cbd98f9ac10c63cd4c45",
  "soul_text_hash": "541cad5062dabf96804991a5bc1d49c208e646d20eda4289878faea09cedba16",
  "resource_registry_commit": "19015beec8cfe8ac067751400a960c9d5af3383f",
  "resources_used": [
    "gov_actions_api",
    "gov_actions_snapshot",
    "drep_vote_history_snapshot",
    "gov_actions_all_snapshot",
    "gov_actions_active_snapshot",
    "gov_action_flags_snapshot",
    "gov_poll_runs_snapshot",
    "top_drep_votes_snapshot"
  ],
  "freshness": {
    "snapshot_age_seconds": 82,
    "max_allowed_seconds": 21600,
    "is_stale": false,
    "snapshot_time": "2026-03-25T13:31:10.615500+00:00"
  },
  "decision_probs": {
    "YES": 0.3738,
    "NO": 0.2323,
    "ABSTAIN": 0.3939
  },
  "uncertainty_band": "MEDIUM",
  "evidence_depth_score": 4,
  "intelligence_profile": "deterministic-v1",
  "missing_evidence_count": 0
}
